odoo8_addon_magentoerpconnect-8.0.3.0.0.99.dev131-py3.8-nspkg.pth
odoo_addons/magentoerpconnect/AUTHORS
odoo_addons/magentoerpconnect/CHANGES.rst
odoo_addons/magentoerpconnect/README.rst
odoo_addons/magentoerpconnect/__init__.py
odoo_addons/magentoerpconnect/__openerp__.py
odoo_addons/magentoerpconnect/backend.py
odoo_addons/magentoerpconnect/connector.py
odoo_addons/magentoerpconnect/consumer.py
odoo_addons/magentoerpconnect/delivery.py
odoo_addons/magentoerpconnect/delivery_view.xml
odoo_addons/magentoerpconnect/exception.py
odoo_addons/magentoerpconnect/invoice.py
odoo_addons/magentoerpconnect/invoice_view.xml
odoo_addons/magentoerpconnect/magento_model.py
odoo_addons/magentoerpconnect/magento_model_view.xml
odoo_addons/magentoerpconnect/magentoerpconnect_data.xml
odoo_addons/magentoerpconnect/magentoerpconnect_menu.xml
odoo_addons/magentoerpconnect/partner.py
odoo_addons/magentoerpconnect/partner_category.py
odoo_addons/magentoerpconnect/partner_view.xml
odoo_addons/magentoerpconnect/payment_method.py
odoo_addons/magentoerpconnect/payment_method_view.xml
odoo_addons/magentoerpconnect/product.py
odoo_addons/magentoerpconnect/product_category.py
odoo_addons/magentoerpconnect/product_view.xml
odoo_addons/magentoerpconnect/related_action.py
odoo_addons/magentoerpconnect/sale.py
odoo_addons/magentoerpconnect/sale_view.xml
odoo_addons/magentoerpconnect/setting.py
odoo_addons/magentoerpconnect/setting_view.xml
odoo_addons/magentoerpconnect/stock_picking.py
odoo_addons/magentoerpconnect/stock_tracking.py
odoo_addons/magentoerpconnect/stock_view.xml
odoo_addons/magentoerpconnect/doc/Makefile
odoo_addons/magentoerpconnect/doc/conf.py
odoo_addons/magentoerpconnect/doc/core
odoo_addons/magentoerpconnect/doc/index.rst
odoo_addons/magentoerpconnect/doc/make.bat
odoo_addons/magentoerpconnect/doc/_static/img/LogicSupply_Orange_260x80_transparent.png
odoo_addons/magentoerpconnect/doc/_static/img/akretion_logo.png
odoo8_addon_magentoerpconnect-8.0.3.0.0.99.dev131.dist-info/METADATA
odoo8_addon_magentoerpconnect-8.0.3.0.0.99.dev131.dist-info/WHEEL
odoo8_addon_magentoerpconnect-8.0.3.0.0.99.dev131.dist-info/namespace_packages.txt
odoo8_addon_magentoerpconnect-8.0.3.0.0.99.dev131.dist-info/top_level.txt
odoo8_addon_magentoerpconnect-8.0.3.0.0.99.dev131.dist-info/RECORD
