Metadata-Version: 2.1
Name: odoo8-addon-magentoerpconnect
Version: 8.0.3.0.0.99.dev131
Summary: Magento Connector
Home-page: http://www.odoo-magento-connector.com
Author: Camptocamp,Akretion,Odoo Community Association (OCA)
Author-email: support@odoo-community.org
License: AGPL-3
Platform: UNKNOWN
Classifier: Programming Language :: Python
Classifier: Framework :: Odoo
Classifier: Framework :: Odoo :: 8.0
Classifier: License :: OSI Approved :: GNU Affero General Public License v3
Requires-Python: ~=2.7
Requires-Dist: magento
Requires-Dist: odoo8-addon-connector-ecommerce
Requires-Dist: odoo8-addon-product-m2mcategories
Requires-Dist: odoo (<9.0a,>=8.0a)
